ultracutpro
