Metadata-Version: 2.2
Name: ultracutpro
Version: 0.0.3
Summary: ultracutpro: AI for cut.
Author: Lucas Jin
Author-email: test@163.com
License: GPL-3.0
Keywords: deep learning,script helper,tools
Platform: any
Requires-Dist: tenacity
Requires-Dist: pysubs2
Requires-Dist: moviepy
Requires-Dist: funasr_onnx
Dynamic: author
Dynamic: author-email
Dynamic: description
Dynamic: keywords
Dynamic: license
Dynamic: platform
Dynamic: requires-dist
Dynamic: summary
